pdetransformer/__init__.py
pdetransformer/setup.py
pdetransformer/utils.py
pdetransformer/visualization.py
pdetransformer/callback/__init__.py
pdetransformer/callback/callbacks.py
pdetransformer/callback/diffusers.py
pdetransformer/callback/ema.py
pdetransformer/callback/ema_clip.py
pdetransformer/callback/setup_callback.py
pdetransformer/callback/simulation_2d_metrics.py
pdetransformer/callback/videos.py
pdetransformer/core/__init__.py
pdetransformer/core/mixed_channels/__init__.py
pdetransformer/core/mixed_channels/dit.py
pdetransformer/core/mixed_channels/factformer.py
pdetransformer/core/mixed_channels/pde_transformer.py
pdetransformer/core/mixed_channels/scot.py
pdetransformer/core/mixed_channels/train_probabilistic.py
pdetransformer/core/mixed_channels/train_supervised.py
pdetransformer/core/mixed_channels/udit.py
pdetransformer/core/mixed_channels/unet.py
pdetransformer/core/separate_channels/__init__.py
pdetransformer/core/separate_channels/pde_transformer.py
pdetransformer/core/separate_channels/tasks.py
pdetransformer/core/separate_channels/train_probabilistic.py
pdetransformer/core/separate_channels/train_supervised.py
pdetransformer/core/separate_channels/utils.py
pdetransformer/data/__init__.py
pdetransformer/data/cached_dataset.py
pdetransformer/data/joint_module.py
pdetransformer/data/metadata_dataset.py
pdetransformer/data/metadata_remapping.py
pdetransformer/data/multi_module.py
pdetransformer/data/pbdl_module.py
pdetransformer/data/script_convert_torchfsm.py
pdetransformer/data/utils.py
pdetransformer/data/pbdl_dataloader/__init__.py
pdetransformer/data/pbdl_dataloader/colors.py
pdetransformer/data/pbdl_dataloader/dataset.py
pdetransformer/data/pbdl_dataloader/fetcher.py
pdetransformer/data/pbdl_dataloader/loader.py
pdetransformer/data/pbdl_dataloader/logging.py
pdetransformer/data/pbdl_dataloader/normalization.py
pdetransformer/data/pbdl_dataloader/utilities.py
pdetransformer/data/pbdl_dataloader/torch/__init__.py
pdetransformer-0.1.11.dist-info/licenses/LICENSE
pdetransformer-0.1.11.dist-info/licenses/LICENSE.txt
pdetransformer-0.1.11.dist-info/METADATA
pdetransformer-0.1.11.dist-info/WHEEL
pdetransformer-0.1.11.dist-info/top_level.txt
pdetransformer-0.1.11.dist-info/RECORD
