Metadata-Version: 2.4
Name: pdetransformer
Version: 0.1.11
Summary: PDE-Transformer: Efficient and Versatile Transformers for Physics Simulations
Author-email: Benjamin Holzschuh <benjamin.holzschuh@tum.de>
License: MIT
Project-URL: Homepage, https://tum-pbs.github.io/pde-transformer/landing.html
Project-URL: Repository, https://github.com/tum-pbs/pde-transformer.git
Classifier: Development Status :: 3 - Alpha
Classifier: Intended Audience :: Science/Research
Classifier: Programming Language :: Python :: 3
Classifier: Programming Language :: Python :: 3.11
Classifier: License :: OSI Approved :: MIT License
Classifier: Operating System :: OS Independent
Classifier: Topic :: Scientific/Engineering :: Physics
Classifier: Topic :: Scientific/Engineering :: Artificial Intelligence
Requires-Python: >=3.11
License-File: LICENSE
License-File: LICENSE.txt
Requires-Dist: lightning>=2.2.5
Requires-Dist: omegaconf>=2.3.0
Requires-Dist: einops>=0.8.1
Requires-Dist: lightning-bolts>=0.7.0
Requires-Dist: torchvision>=0.18.0
Requires-Dist: matplotlib>=3.7.0
Requires-Dist: diffusers>=0.28.2
Requires-Dist: torch-fidelity>=0.3.0
Requires-Dist: wandb>=0.17.0
Requires-Dist: numpy>=1.26.4
Requires-Dist: transformers>=4.42.3
Requires-Dist: accelerate>=0.30.1
Requires-Dist: moviepy>=1.0.3
Requires-Dist: pandas>=2.2.2
Requires-Dist: imageio>=2.34.2
Requires-Dist: timm>=1.0.12
Requires-Dist: seaborn>=0.13.2
Requires-Dist: torchprofile>=0.0.4
Requires-Dist: h5py>=3.11.0
Requires-Dist: vape4d>=0.2.7
Dynamic: license-file
